Vipackage/__init__.py
Vipackage/medToolkit.py
Vipackage/data/10mb.zip
Vipackage/data/big_buck_bunny_240p_10mb.mp4
Vipackage-1.0.dist-info/METADATA
Vipackage-1.0.dist-info/WHEEL
Vipackage-1.0.dist-info/top_level.txt
Vipackage-1.0.dist-info/RECORD
