Metadata-Version: 2.1
Name: Vipackage
Version: 1.0
Summary: Custom package
Download-URL: https://sample-videos.com/zip/10mb.zip
Author: VigneshVallavan
Author-email: vigneshvallavan1999@gmail.com
Classifier: Programming Language :: Python :: 3
Classifier: License :: OSI Approved :: MIT License
Classifier: Operating System :: OS Independent
